{
  "PackageData": [
    {
      "Row": [
        {
          "SchemaColumnUId": "ae0e45ca-c495-4fe7-a39d-3ab7278e1617",
          "ColumnName": "Id",
          "Value": "382b64c0-4397-4c38-9970-9e8966573d65"
        },
        {
          "SchemaColumnUId": "736c30a7-c0ec-4fa9-b034-2552b319b633",
          "ColumnName": "Name",
          "Value": ""
        },
        {
          "SchemaColumnUId": "9e53fd7c-dde4-4502-a64c-b9e34148108b",
          "ColumnName": "Description",
          "Value": ""
        }
      ]
    },
    {
      "Row": [
        {
          "SchemaColumnUId": "ae0e45ca-c495-4fe7-a39d-3ab7278e1617",
          "ColumnName": "Id",
          "Value": "3aeb6b96-fe4b-4927-bc54-fa85e374d233"
        },
        {
          "SchemaColumnUId": "736c30a7-c0ec-4fa9-b034-2552b319b633",
          "ColumnName": "Name",
          "Value": ""
        },
        {
          "SchemaColumnUId": "9e53fd7c-dde4-4502-a64c-b9e34148108b",
          "ColumnName": "Description",
          "Value": ""
        }
      ]
    },
    {
      "Row": [
        {
          "SchemaColumnUId": "ae0e45ca-c495-4fe7-a39d-3ab7278e1617",
          "ColumnName": "Id",
          "Value": "81e05731-1292-4c13-8909-a3d3141a5772"
        },
        {
          "SchemaColumnUId": "736c30a7-c0ec-4fa9-b034-2552b319b633",
          "ColumnName": "Name",
          "Value": ""
        },
        {
          "SchemaColumnUId": "9e53fd7c-dde4-4502-a64c-b9e34148108b",
          "ColumnName": "Description",
          "Value": ""
        }
      ]
    },
    {
      "Row": [
        {
          "SchemaColumnUId": "ae0e45ca-c495-4fe7-a39d-3ab7278e1617",
          "ColumnName": "Id",
          "Value": "911493a7-2b50-4ca6-8683-f4f2dada6a50"
        },
        {
          "SchemaColumnUId": "736c30a7-c0ec-4fa9-b034-2552b319b633",
          "ColumnName": "Name",
          "Value": ""
        },
        {
          "SchemaColumnUId": "9e53fd7c-dde4-4502-a64c-b9e34148108b",
          "ColumnName": "Description",
          "Value": ""
        }
      ]
    }
  ]
}